MANIFEST.in
README.rst
requirements-docs.txt
requirements-test.txt
requirements.txt
setup.cfg
setup.py
src/django_inspectional_registration.egg-info/PKG-INFO
src/django_inspectional_registration.egg-info/SOURCES.txt
src/django_inspectional_registration.egg-info/dependency_links.txt
src/django_inspectional_registration.egg-info/requires.txt
src/django_inspectional_registration.egg-info/top_level.txt
src/django_inspectional_registration.egg-info/zip-safe
src/registration/__init__.py
src/registration/compat.py
src/registration/conf.py
src/registration/forms.py
src/registration/models.py
src/registration/signals.py
src/registration/urls.py
src/registration/utils.py
src/registration/views.py
src/registration/admin/__init__.py
src/registration/admin/forms.py
src/registration/backends/__init__.py
src/registration/backends/base.py
src/registration/backends/default/__init__.py
src/registration/contrib/__init__.py
src/registration/contrib/autologin/__init__.py
src/registration/contrib/autologin/conf.py
src/registration/contrib/autologin/models.py
src/registration/contrib/autologin/tests.py
src/registration/contrib/notification/__init__.py
src/registration/contrib/notification/conf.py
src/registration/contrib/notification/models.py
src/registration/contrib/notification/tests/__init__.py
src/registration/contrib/notification/tests/urls.py
src/registration/locale/de/LC_MESSAGES/django.mo
src/registration/locale/de/LC_MESSAGES/django.po
src/registration/locale/fr/LC_MESSAGES/django.mo
src/registration/locale/fr/LC_MESSAGES/django.po
src/registration/locale/ja/LC_MESSAGES/django.mo
src/registration/locale/ja/LC_MESSAGES/django.po
src/registration/locale/pt_BR/LC_MESSAGES/django.mo
src/registration/locale/pt_BR/LC_MESSAGES/django.po
src/registration/locale/zh-hans/LC_MESSAGES/django.mo
src/registration/locale/zh-hans/LC_MESSAGES/django.po
src/registration/locale/zh_Hans/LC_MESSAGES/django.mo
src/registration/locale/zh_Hans/LC_MESSAGES/django.po
src/registration/management/__init__.py
src/registration/management/commands/__init__.py
src/registration/management/commands/cleanup_expired_registrations.py
src/registration/management/commands/cleanup_registrations.py
src/registration/management/commands/cleanup_rejected_registrations.py
src/registration/management/commands/cleanupregistration.py
